captchakings/__init__.py
captchakings/client.py
captchakings/exceptions.py
captchakings-1.0.1.dist-info/licenses/LICENSE
captchakings-1.0.1.dist-info/METADATA
captchakings-1.0.1.dist-info/WHEEL
captchakings-1.0.1.dist-info/top_level.txt
captchakings-1.0.1.dist-info/RECORD
