Metadata-Version: 2.4
Name: captchakings
Version: 1.0.1
Summary: Official Python client for CaptchaKings API
Home-page: https://captchakings.com
Author: CaptchaKings
Author-email: support@captchakings.com
Project-URL: Documentation, https://captchakings.com?section=documentation
Project-URL: Source, https://captchakings.com
Project-URL: Bug Reports, https://captchakings.com
Keywords: captcha,ocr,captcha-solver,captchakings,api-client
Classifier: Development Status :: 5 - Production/Stable
Classifier: Intended Audience :: Developers
Classifier: Topic :: Software Development :: Libraries :: Python Modules
Classifier: License :: OSI Approved :: MIT License
Classifier: Programming Language :: Python :: 3
Classifier: Programming Language :: Python :: 3.6
Classifier: Programming Language :: Python :: 3.7
Classifier: Programming Language :: Python :: 3.8
Classifier: Programming Language :: Python :: 3.9
Classifier: Programming Language :: Python :: 3.10
Classifier: Programming Language :: Python :: 3.11
Requires-Python: >=3.6
License-File: LICENSE
Requires-Dist: requests>=2.25.0
Dynamic: author
Dynamic: author-email
Dynamic: classifier
Dynamic: description
Dynamic: description-content-type
Dynamic: home-page
Dynamic: keywords
Dynamic: license-file
Dynamic: project-url
Dynamic: requires-dist
Dynamic: requires-python
Dynamic: summary
